data_cleaner_bonc/__init__.py
data_cleaner_bonc/cleaner_util.py
str_data_cleaner-0.0.1.dist-info/METADATA
str_data_cleaner-0.0.1.dist-info/WHEEL
str_data_cleaner-0.0.1.dist-info/top_level.txt
str_data_cleaner-0.0.1.dist-info/zip-safe
str_data_cleaner-0.0.1.dist-info/RECORD
