Metadata-Version: 2.1
Name: str_data_cleaner
Version: 0.0.1
Summary: 清理标讯工具包
Requires-Dist: bs4==0.0.2
